aiodiscourse/__init__.py
aiodiscourse/cli.py
aiodiscourse/client.py
aiodiscourse/exceptions.py
aiodiscourse/py.typed
aiodiscourse/retry.py
aiodiscourse/namespaces/admin.py
aiodiscourse/namespaces/categories.py
aiodiscourse/namespaces/groups.py
aiodiscourse/namespaces/notifications.py
aiodiscourse/namespaces/posts.py
aiodiscourse/namespaces/search.py
aiodiscourse/namespaces/tags.py
aiodiscourse/namespaces/topics.py
aiodiscourse/namespaces/uploads.py
aiodiscourse/namespaces/users.py
aiodiscourse-0.3.0.dist-info/licenses/LICENSE
aiodiscourse-0.3.0.dist-info/METADATA
aiodiscourse-0.3.0.dist-info/WHEEL
aiodiscourse-0.3.0.dist-info/entry_points.txt
aiodiscourse-0.3.0.dist-info/top_level.txt
aiodiscourse-0.3.0.dist-info/RECORD
