Metadata-Version: 2.4
Name: aiodiscourse
Version: 0.3.0
Summary: Async client for Discourse API
Author-email: Andrew Sawyers <andrew@sawdog.com>
License: MIT
Classifier: Programming Language :: Python :: 3
Classifier: License :: OSI Approved :: MIT License
Classifier: Operating System :: OS Independent
Requires-Python: >=3.13
License-File: LICENSE
Requires-Dist: aiohttp
Requires-Dist: arrow
Provides-Extra: dev
Requires-Dist: pytest; extra == "dev"
Requires-Dist: pytest-asyncio; extra == "dev"
Provides-Extra: cli
Requires-Dist: click; extra == "cli"
Requires-Dist: dotenv; extra == "cli"
Dynamic: license-file
